gradio_sourceviewer/__init__.py
gradio_sourceviewer/sourceviewer.py
gradio_sourceviewer/sourceviewer.pyi
gradio_sourceviewer/templates/component/__vite-browser-external-2447137e.js
gradio_sourceviewer/templates/component/index.js
gradio_sourceviewer/templates/component/module-2c3384e6.js
gradio_sourceviewer/templates/component/module-5eba924d.js
gradio_sourceviewer/templates/component/module-a5e22de5.js
gradio_sourceviewer/templates/component/style.css
gradio_sourceviewer/templates/component/wrapper-6f348d45-19fa94bf.js
gradio_sourceviewer/templates/example/index.js
gradio_sourceviewer/templates/example/style.css
gradio_sourceviewer-1.0.0.dist-info/METADATA
gradio_sourceviewer-1.0.0.dist-info/WHEEL
gradio_sourceviewer-1.0.0.dist-info/RECORD
