Metadata-Version: 2.3
Name: gradio_sourceviewer
Version: 1.0.0
Summary: Python library for easily interacting with trained machine learning models
Author-email: clement.pages@irit.fr
License: Apache-2.0
Keywords: gradio-custom-component,gradio-template-Audio,pixit,pyannote-audio,source-separation,speaker-diarization,speech-separation,totatonet
Classifier: Development Status :: 3 - Alpha
Classifier: License :: OSI Approved :: Apache Software License
Classifier: Operating System :: OS Independent
Classifier: Programming Language :: Python :: 3
Classifier: Programming Language :: Python :: 3 :: Only
Classifier: Programming Language :: Python :: 3.10
Classifier: Programming Language :: Python :: 3.11
Classifier: Topic :: Scientific/Engineering
Classifier: Topic :: Scientific/Engineering :: Artificial Intelligence
Classifier: Topic :: Scientific/Engineering :: Visualization
Requires-Python: >=3.8
Requires-Dist: gradio<5.0,>=4.0
Provides-Extra: dev
Requires-Dist: build; extra == 'dev'
Requires-Dist: twine; extra == 'dev'
